pymagba-0.1.0.dist-info/METADATA
pymagba-0.1.0.dist-info/WHEEL
pymagba-0.1.0.dist-info/licenses/LICENSE
pymagba/transform.py
pymagba/__init__.py
pymagba/util.py
pymagba/fields/__init__.py
pymagba/fields/_fields.py
pymagba/sources/__init__.py
pymagba/sources/_sources.py
pymagba/pymagba_binding.cpython-310-x86_64-linux-gnu.so
pymagba-0.1.0.dist-info/RECORD
