Metadata-Version: 2.4
Name: pymagba
Version: 0.1.0
Classifier: Programming Language :: Python :: 3
Classifier: License :: OSI Approved :: BSD License
Classifier: Operating System :: OS Independent
Requires-Dist: numpy >2.0
Requires-Dist: scipy
License-File: LICENSE
Summary: Performant magnetic computation powered by Rust
Author-email: Sira Pornsiriprasert <code@psira.me>
Requires-Python: >=3.10, <3.13
